aggrigator/__init__.py
aggrigator/datasets.py
aggrigator/methods.py
aggrigator/optimized_gearys.py
aggrigator/optimized_morans.py
aggrigator/plotting.py
aggrigator/strategylist.py
aggrigator/summary.py
aggrigator/uncertainty_maps.py
aggrigator/util.py
aggrigator-0.1.0b1.dist-info/licenses/LICENSE
aggrigator-0.1.0b1.dist-info/METADATA
aggrigator-0.1.0b1.dist-info/WHEEL
aggrigator-0.1.0b1.dist-info/top_level.txt
aggrigator-0.1.0b1.dist-info/RECORD
