Metadata-Version: 2.4
Name: aggrigator
Version: 0.1.0b1
Summary: A Python package for aggregation tasks
Author-email: Christoph Karg <christoph.karg@mdc-berlin.de>
License: MIT License
Project-URL: Homepage, https://github.com/Kainmueller-Lab/aggrigator
Project-URL: Repository, https://github.com/Kainmueller-Lab/aggrigator
Requires-Python: >=3.10
License-File: LICENSE
Requires-Dist: numpy>=2.0
Requires-Dist: pandas
Requires-Dist: scipy
Requires-Dist: matplotlib
Requires-Dist: seaborn
Requires-Dist: torch
Requires-Dist: torchvision
Requires-Dist: ipython
Requires-Dist: scikit-learn
Requires-Dist: scikit-image
Requires-Dist: libpysal
Requires-Dist: openpyxl
Requires-Dist: numba
Provides-Extra: dev
Requires-Dist: pytest<8.0,>=7.2; extra == "dev"
Dynamic: license-file
